{
  "name": "SpeakerDesk",
  "fields": [
    {
      "fieldName": "name",
      "fieldType": "String",
      "fieldValidateRules": ["required"]
    },
    {
      "fieldName": "note",
      "fieldType": "String",
      "fieldValidateRules": ["required"]
    },
    {
      "fieldName": "imgLink",
      "fieldType": "String",
      "fieldValidateRules": ["required"]
    },
    {
      "fieldName": "img",
      "fieldType": "byte[]",
      "fieldTypeBlobContent": "image",
      "fieldValidateRules": ["maxbytes"],
      "fieldValidateRulesMaxbytes": "15360"
    }
  ],
  "relationships": [],
  "changelogDate": "20220303052648",
  "entityTableName": "speaker_desk",
  "dto": "mapstruct",
  "pagination": "pagination",
  "service": "serviceImpl",
  "jpaMetamodelFiltering": false,
  "fluentMethods": true,
  "readOnly": false,
  "embedded": false,
  "clientRootFolder": "",
  "applications": "*"
}
